pbnj/__init__.py
pbnj/bot.py
pbnj/connection.py
pbnj/logger.py
pbnj/models.py
pbnj-0.3.3.dist-info/LICENSE.txt
pbnj-0.3.3.dist-info/METADATA
pbnj-0.3.3.dist-info/WHEEL
pbnj-0.3.3.dist-info/top_level.txt
pbnj-0.3.3.dist-info/RECORD
