Metadata-Version: 2.1
Name: pbnj
Version: 0.3.3
Summary: an IRC bot library and framework, focused on simplicity and portability
Home-page: https://github.com/delucks/pbnj
Author: James Luck
Author-email: me@jamesluck.com
License: GNU GPLv3
Download-URL: https://github.com/delucks/pbnj/tarball/v0.3.3
Keywords: irc,chatbot,bot,portable,framework
Platform: UNKNOWN
